setup.py
kcwversion/__init__.py
kcwversion.egg-info/PKG-INFO
kcwversion.egg-info/SOURCES.txt
kcwversion.egg-info/dependency_links.txt
kcwversion.egg-info/entry_points.txt
kcwversion.egg-info/top_level.txt