Metadata-Version: 1.2
Name: kcwversion
Version: 3.0
Summary: kcwversion版本管理
Home-page: UNKNOWN
Author: 百里-坤坤
Author-email: kcwebs@kwebapp.cn
Maintainer: 坤坤
Maintainer-email: fk1402936534@qq.com
License: MIT License
Keywords: kcws3.0
Platform: UNKNOWN
